minha_aposta/__init__.py
minha_aposta/duplasena.py
minha_aposta/lotofacil.py
minha_aposta/megasena.py
minha_aposta/quina.py
minha_aposta-0.0.1.dist-info/METADATA
minha_aposta-0.0.1.dist-info/WHEEL
minha_aposta-0.0.1.dist-info/top_level.txt
minha_aposta-0.0.1.dist-info/RECORD
