Metadata-Version: 2.1
Name: minha-aposta
Version: 0.0.1
Summary: Meu pacote de apostas
Home-page: https://github.com/NetoTricca/minha_aposta_package
Author: netotricca
Author-email: netotricca@gmail.com
License: UNKNOWN
Platform: UNKNOWN
Requires-Python: >=3.8
